canaryScripts/__init__.py
canaryScripts/canary_driver.py
canaryScripts/canary_scraper.py
canaryScripts/canary_shark.py
canaryScripts/network_initializer.py
canaryServices/__init__.py
canaryServices/attacker.py
canaryServices/node.py
tests/__init__.py
tests/test_canary.py
canary_pkg_whoward3-1.0.1.dist-info/LICENSE
canary_pkg_whoward3-1.0.1.dist-info/METADATA
canary_pkg_whoward3-1.0.1.dist-info/WHEEL
canary_pkg_whoward3-1.0.1.dist-info/top_level.txt
canary_pkg_whoward3-1.0.1.dist-info/RECORD
