Metadata-Version: 2.1
Name: canary-pkg-whoward3
Version: 1.0.1
Summary: A collection of python scripts for distributed DDoS Detection Simulations using CORE
Home-page: https://github.com/whoward3/canary
Author: Winston Howard
Author-email: winston.howard@yahoo.com
License: UNKNOWN
Platform: UNKNOWN
Classifier: Programming Language :: Python :: 3
Classifier: License :: OSI Approved :: GNU General Public License v3 (GPLv3)
Classifier: Operating System :: POSIX :: Linux
Requires-Python: >=3.6
